{
	"backtraceGraph" : 
	{
		"commands" : 
		[
			"install"
		],
		"files" : 
		[
			"python_gym/CMakeLists.txt"
		],
		"nodes" : 
		[
			{
				"file" : 0
			},
			{
				"command" : 0,
				"file" : 0,
				"line" : 1,
				"parent" : 0
			}
		]
	},
	"installers" : 
	[
		{
			"backtrace" : 1,
			"component" : "Unspecified",
			"destination" : "include/gym/python_gym",
			"paths" : 
			[
				"python_gym/python_env.h",
				"python_gym/python_env.tpp",
				"python_gym/atari_wrappers.py"
			],
			"type" : "file"
		}
	],
	"paths" : 
	{
		"build" : "python_gym",
		"source" : "python_gym"
	}
}
